nonebot_plugin_zssm-0.3.7.dist-info/METADATA
nonebot_plugin_zssm-0.3.7.dist-info/WHEEL
nonebot_plugin_zssm-0.3.7.dist-info/entry_points.txt
nonebot_plugin_zssm/__init__.py
nonebot_plugin_zssm/api.py
nonebot_plugin_zssm/browser/__init__.py
nonebot_plugin_zssm/browser/browser.py
nonebot_plugin_zssm/browser/installer.py
nonebot_plugin_zssm/config.py
nonebot_plugin_zssm/handle.py
nonebot_plugin_zssm/processors/__init__.py
nonebot_plugin_zssm/processors/ai.py
nonebot_plugin_zssm/processors/image.py
nonebot_plugin_zssm/processors/pdf.py
nonebot_plugin_zssm/processors/web.py
nonebot_plugin_zssm/prompt.txt
nonebot_plugin_zssm-0.3.7.dist-info/RECORD
