Metadata-Version: 2.1
Name: nonebot-plugin-zssm
Version: 0.3.7
Summary: 这是什么？问一下！用 ai 来解释群友发送的「未知」内容
Author-Email: djkcyl <cyl@cyllive.cn>
License: MIT
Requires-Python: >=3.12
Requires-Dist: nonebot2[fastapi,websockets]
Requires-Dist: nonebot-plugin-alconna>=0.57.2
Requires-Dist: httpx>=0.28.1
Requires-Dist: playwright>=1.51.0
Requires-Dist: pillow>=11.0.0
Requires-Dist: pymupdf>=1.25.5
